simple.v
module voter (I, O);
input [3:0] I; // I 4 men
output [3:1] O; // O Result
reg [3:1] O; 

always@ (I)
case (I)
   4'b0000: O=3'b001;
   4'b0001: O=3'b001;
   4'b0010: O=3'b001;
   4'b0011: O=3'b010;
   4'b0100: O=3'b001;
   4'b0101: O=3'b010;
   4'b0110: O=3'b010;
   4'b0111: O=3'b100;
   4'b1000: O=3'b001;
   4'b1001: O=3'b010;
   4'b1010: O=3'b010;
   4'b1011: O=3'b100;
   4'b1100: O=3'b010;
   4'b1101: O=3'b100;
   4'b1110: O=3'b100;
   4'b1111: O=3'b100;
   default: O=3'b000;
endcase
endmodule

simple_tb.v
// `include "nonblocking.v"
module voter_tb;
reg [3:0] I_tb;
wire [3:1] O_tb;
initial begin
$dumpfile("voter.vcd");
$dumpvars(0,v_tb);
#10 I_tb= 4'b0000;
#10 I_tb= 4'b0001;
#10 I_tb= 4'b0010;
#10 I_tb= 4'b0011;
#10 I_tb= 4'b0100;
#10 I_tb= 4'b0101;
#10 I_tb= 4'b0110;
#10 I_tb= 4'b0111;
#10 I_tb= 4'b1000;
#10 I_tb= 4'b1001;
#10 I_tb= 4'b1010;
#10 I_tb= 4'b1011;
#10 I_tb= 4'b1100;
#10 I_tb= 4'b1101;
#10 I_tb= 4'b1110;
#10 I_tb= 4'b1111;
#10 $finish;
end
voter v_tb(I_tb,O_tb);
endmodule

voter.vcd
$date
	Thu Apr 14 22:13:44 2022
$end
$version
	Icarus Verilog
$end
$timescale
	1s
$end
$scope module voter_tb $end
$scope module v_tb $end
$var wire 4 ! I [3:0] $end
$var reg 3 " O [3:1] $end
$upscope $end
$upscope $end
$enddefinitions $end
#0
$dumpvars
bx "
bx !
$end
#10
b1 "
b0 !
#20
b1 !
#30
b10 !
#40
b10 "
b11 !
#50
b1 "
b100 !
#60
b10 "
b101 !
#70
b110 !
#80
b100 "
b111 !
#90
b1 "
b1000 !
#100
b10 "
b1001 !
#110
b1010 !
#120
b100 "
b1011 !
#130
b10 "
b1100 !
#140
b100 "
b1101 !
#150
b1110 !
#160
b1111 !
